pylint_runner/__init__.py
pylint_runner/main.py
pylint_runner/utils.py
pylint_runner-0.7.0.dist-info/LICENSE
pylint_runner-0.7.0.dist-info/METADATA
pylint_runner-0.7.0.dist-info/WHEEL
pylint_runner-0.7.0.dist-info/entry_points.txt
pylint_runner-0.7.0.dist-info/top_level.txt
pylint_runner-0.7.0.dist-info/RECORD
